
<puzzle id="MTC" class="sqm.matchsticks">
	<challenge id="171">
		<date>2022.28.07.04.07.09</date>
	<designer>
		<name type="author" id="UNA">Unknown Author</name>
	</designer>
		<title>The Sand Timer</title>
		<setup goal="image:generate"  move-type="move"   >
			<rules type="text"> 
                The puzzle by Nobuyuki Yoshigahara.
			</rules>
<piece id="1" base="0" rotation="90" meet_ends="0,1" shift="0,0"/><piece id="2" base="1" rotation="90" meet_ends="1,0" shift="0,0"/><piece id="3" base="2" rotation="330" meet_ends="1,0" shift="0,0"/><piece id="4" base="3" rotation="330" meet_ends="1,0" shift="0,0"/><piece id="5" base="4" rotation="330" meet_ends="1,0" shift="0,0"/><piece id="6" base="5" rotation="90" meet_ends="1,0" shift="0,0"/><piece id="7" base="1" rotation="30" meet_ends="0,0" shift="0,0"/><piece id="8" base="7" rotation="30" meet_ends="1,0" shift="0,0"/><piece id="9" base="8" rotation="30" meet_ends="1,0" shift="0,0"/> 
           
                 
                                                <solution type="generate">
                                                                <piece id="1" base="6" rotation="90" meet_ends="1,0" shift="0,0"/>
                                                                <piece id="7" base="2" rotation="30" meet_ends="0,0" shift="0,0"/>
                                                                <piece id="8" base="3" rotation="30" meet_ends="1,0" shift="0,0"/>
                                                                <piece id="9" base="6" rotation="30" meet_ends="1,1" shift="1,0"/> 
                                               </solution> 
                                                <solution type="generate">
                                                                <piece id="3" base="9" rotation="330" meet_ends="1,1" shift="0,0"/>
                                                                <piece id="4" base="8" rotation="330" meet_ends="0,0" shift="0,0"/>
                                                                <piece id="5" base="8" rotation="330" meet_ends="1,0" shift="1,0"/>
                                                                <piece id="2" base="6" rotation="90" meet_ends="0,1" shift="0,0"/> 
                                               </solution>
	   </setup>       
	</challenge>
</puzzle> 
